README.rst
setup.py
panopy/__init__.py
panopy/pano.py
panopy.egg-info/PKG-INFO
panopy.egg-info/SOURCES.txt
panopy.egg-info/dependency_links.txt
panopy.egg-info/entry_points.txt
panopy.egg-info/not-zip-safe
panopy.egg-info/requires.txt
panopy.egg-info/top_level.txt