Metadata-Version: 1.0
Name: panopy
Version: 0.2.3
Summary: Pandoc wrapper with templates
Home-page: https://github.com/balachia/panopy
Author: Tony Vashevko 
Author-email: avashevko@gmail.com
License: LICENSE.txt
Keywords: pandoc
Platform: UNKNOWN
